LICENSE
MANIFEST.in
README.rst
setup.cfg
setup.py
djangocms_masonry/__init__.py
djangocms_masonry/cms_plugins.py
djangocms_masonry/conf.py
djangocms_masonry/models.py
djangocms_masonry.egg-info/PKG-INFO
djangocms_masonry.egg-info/SOURCES.txt
djangocms_masonry.egg-info/dependency_links.txt
djangocms_masonry.egg-info/not-zip-safe
djangocms_masonry.egg-info/pbr.json
djangocms_masonry.egg-info/requires.txt
djangocms_masonry.egg-info/top_level.txt
djangocms_masonry/migrations/0001_initial.py
djangocms_masonry/migrations/__init__.py
djangocms_masonry/south_migrations/0001_initial.py
djangocms_masonry/south_migrations/__init__.py
djangocms_masonry/static/djangocms_masonry/bower_components/masonry/masonry.js
djangocms_masonry/static/djangocms_masonry/bower_components/masonry/dist/masonry.pkgd.js
djangocms_masonry/static/djangocms_masonry/bower_components/masonry/dist/masonry.pkgd.min.js
djangocms_masonry/static/djangocms_masonry/bower_components/masonry/sandbox/basic.html
djangocms_masonry/static/djangocms_masonry/bower_components/masonry/sandbox/bottom-up.html
djangocms_masonry/static/djangocms_masonry/bower_components/masonry/sandbox/element-sizing.html
djangocms_masonry/static/djangocms_masonry/bower_components/masonry/sandbox/fit-width.html
djangocms_masonry/static/djangocms_masonry/bower_components/masonry/sandbox/fluid.html
djangocms_masonry/static/djangocms_masonry/bower_components/masonry/sandbox/jquery.html
djangocms_masonry/static/djangocms_masonry/bower_components/masonry/sandbox/right-to-left.html
djangocms_masonry/static/djangocms_masonry/bower_components/masonry/sandbox/sandbox.css
djangocms_masonry/static/djangocms_masonry/bower_components/masonry/sandbox/stamps.html
djangocms_masonry/static/djangocms_masonry/bower_components/masonry/sandbox/browserify/index.html
djangocms_masonry/static/djangocms_masonry/bower_components/masonry/sandbox/browserify/main.js
djangocms_masonry/static/djangocms_masonry/bower_components/masonry/sandbox/require-js/index.html
djangocms_masonry/static/djangocms_masonry/bower_components/masonry/sandbox/require-js/main.js
djangocms_masonry/templates/djangocms_masonry/base.html
djangocms_masonry/templates/djangocms_masonry/default.html