Metadata-Version: 1.1
Name: djangocms-masonry
Version: 0.1.0
Summary: Djangocms plugin for masonry carousel v1
Home-page: https://github.com/digital-anvil/djangocms-masonry
Author: Lee Solway
Author-email: lee@digitalanvil.co.uk
License: BSD
Keywords: djangocms-masonry
Platform: UNKNOWN
Classifier: Development Status :: 2 - Pre-Alpha
Classifier: Framework :: Django
Classifier: Intended Audience :: Developers
Classifier: License :: OSI Approved :: BSD License
Classifier: Natural Language :: English
Classifier: Programming Language :: Python :: 2
Classifier: Programming Language :: Python :: 2.7
